xicam/_version.py
xicam/run_headless.py
xicam/run_xicam.py
xicam/core/__init__.py
xicam/core/paths.py
xicam/core/args/__init__.py
xicam/core/data/__init__.py
xicam/core/data/bluesky_utils.py
xicam/core/execution/__init__.py
xicam/core/execution/camlinkexecutor.py
xicam/core/execution/daskexecutor.py
xicam/core/execution/localexecutor.py
xicam/core/execution/workflow.py
xicam/core/formats/NPYPlugin.py
xicam/core/formats/__init__.py
xicam/core/intents/__init__.py
xicam/core/msg/__init__.py
xicam/core/operations/__init__.py
xicam/core/tests/fixtures.py
xicam/core/tests/test_data.py
xicam/core/tests/test_msg.py
xicam/core/tests/test_threads.py
xicam/core/tests/test_workflow_.py
xicam/core/tests/workflow_fixtures.py
xicam/core/threads/__init__.py
xicam/core/workspace/__init__.py
xicam/gui/__init__.py
xicam/gui/actions/__init__.py
xicam/gui/bluesky/__init__.py
xicam/gui/bluesky/databroker_catalog_plugin.py
xicam/gui/bluesky/search.py
xicam/gui/bluesky/utils.py
xicam/gui/cammart/__init__.py
xicam/gui/cammart/packagemanager.py
xicam/gui/cammart/venvs.py
xicam/gui/canvases/__init__.py
xicam/gui/canvasmanager/__init__.py
xicam/gui/clientonlymodels/LocalFileSystemResource.py
xicam/gui/clientonlymodels/__init__.py
xicam/gui/connections/__init__.py
xicam/gui/delegates/__init__.py
xicam/gui/delegates/lineedit.py
xicam/gui/models/__init__.py
xicam/gui/models/treemodel.py
xicam/gui/models/tests/test_treemodel.py
xicam/gui/patches/PyQtGraph.py
xicam/gui/patches/__init__.py
xicam/gui/plugins/__init__.py
xicam/gui/plugins/ensembleguiplugin.py
xicam/gui/settings/__init__.py
xicam/gui/settings/appearance.py
xicam/gui/settings/databroker.py
xicam/gui/settings/execution.py
xicam/gui/settings/logging.py
xicam/gui/static/__init__.py
xicam/gui/static/__pycache__/__init__.cpython-38.pyc
xicam/gui/static/fonts/zerothre.ttf
xicam/gui/static/icons/1x1hor.png
xicam/gui/static/icons/1x1vert.png
xicam/gui/static/icons/2x1grid.png
xicam/gui/static/icons/2x2grid.png
xicam-2.4.6.dist-info/LICENSE.md
xicam-2.4.6.dist-info/METADATA
xicam-2.4.6.dist-info/WHEEL
xicam-2.4.6.dist-info/entry_points.txt
xicam-2.4.6.dist-info/top_level.txt
xicam-2.4.6.dist-info/RECORD
